sign/__init__.py
sign/get_name.py
floxsign-0.1.dist-info/LICENSE
floxsign-0.1.dist-info/METADATA
floxsign-0.1.dist-info/WHEEL
floxsign-0.1.dist-info/top_level.txt
floxsign-0.1.dist-info/RECORD
