Metadata-Version: 2.1
Name: floxsign
Version: 0.1
Summary: A package to helps with symbols in python like gettingn the name of a symbol.
Home-page: https://github.com/Flox-Company/floxsign
Author: Florian Ratgers
Author-email: flox@ratgers.nl
Classifier: Programming Language :: Python :: 3
Classifier: License :: OSI Approved :: MIT License
Classifier: Operating System :: OS Independent
Requires-Python: >=3.6
License-File: LICENSE
